{
  "name": "Argumentum - Fallacies - Back - English",
  "notes": "",
  "dpi": 300,
  "live": true,
  "psize": "letter",
  "pori": "landscape",
  "csize": "tarot",
  "cori": "portrait",
  "cheight": "",
  "cwidth": "",
  "cunit": "mm",
  "ccircle": false,
  "gsize": 0,
  "gunit": "mm",
  "msize": 0.5,
  "munit": "in",
  "blsize": 0,
  "blunit": "in",
  "ssize": 0,
  "sunit": "in",
  "cutline": true,
  "bradius": 0.125,
  "brunit": "in",
  "overlay": false,
  "oopa": 1,
  "oURL": "",
  "extCSS": "https://fonts.googleapis.com/css2?family=Bebas+Neue&family=PT+Sans:wght@700&display=swap",
  "css": "@import url('https://fonts.cdnfonts.com/css/dinpro');\n\ncard { \n  font-size: 50%;\n  font-family: 'DINPro', sans-serif;\n}\n\n.cardpenBleed {\n\tborder:0 !important;\n}\n\n.cardContainer {\n  width:100%;\n  height:100%;\n  position:relative;\n  background:url('../../Fallacies/Assets/Fallacy-back/Fallacy-back-bg.jpg') repeat;\n  background-size:100% 100%;\n  border-radius:0.125in;\n  overflow:hidden;\n}\n\n.cardContent {\n  position:absolute;\n  top:0;\n  z-index:2;\n  width:100%;\n  height:100%;\n  display:flex;\n  flex-flow:column wrap;\n  justify-content:space-between;\n}\n\n/* Vibrant red vignette effect*/\n.vignetteOverlay {\n  width:200%;\n  height:100%;\n  position:relative;\n  left:-25%;\n\t-webkit-box-shadow:inset 3px 7px 70px 30px rgba(180, 0, 3,0.7);\n    -moz-box-shadow: inset 3px 7px 70px 30px rgba(180, 0, 3,0.7);\n    box-shadow: inset 3px 0px 40px 30px rgba(180, 0, 3,0.6);\n}\n\n/* Dark vignette effect*/\n.vignetteOverlay2 {\n  width:150%;\n  height:100%;\n  position:absolute;\n  top:0;\n  left:-25%;\n  -webkit-box-shadow: inset 3px 7px 63px 4px #000);\n  -moz-box-shadow: inset 3px 7px 63px 4px #000;\n  box-shadow: inset 3px 0px 40px 0px rgba(0,0,0,0.8);\n}\n\n.title {\n  display:flex;\n  flex-flow:column;\n  word-wrap:break-word;\n  position:relative;\n  width:90%;\n  height:54%;\n  max-height:3.2em;\n  padding:9% 12% 0% 9%;\n  font-weight:900;\n  font-size:8em;\n  line-height:0.85;\n  fill:#fff3de;\n  letter-spacing:0.03em;\n  align-items:flex-start;\n  z-index:3;\n}\n\n.title svg {\n\tmargin-bottom:4%;\n  \theight:29%\n}\n.title svg text {\n\tletter-spacing:0.09em;\n  \tfont-size:100px;\n    color:red;\n    stroke:#720000;\n    stroke-width:2px;\n    stroke-linecap:butt;\n    stroke-linejoin:miter;\n    stroke-opacity:0.3;\n}\n\n.pieces {\n  \theight:54%;\n  \tposition:absolute;\n  \tz-index:1;\n  \ttop:36%;\n  \tright:0;\n  \ttext-align:center;\n}\n\n.pieces img {\n  width:95%;\n}\n.footer {\n\tcolor:#fff3de;\n  \ttext-transform:uppercase;\n  \twidth:100%;\n  \ttext-align:center;\n  \tfont-family:'Bebas Neue';\n  \tletter-spacing:0.15em;\n  \tfont-size:2.1em;\n  \tfill:#fff3de;\n  \tpadding-bottom:0.25em;\n}\n\n",
  "csv": "tagline_fr,tagline_en\n\"l'art de ne janais avoir tort\",\"The art of never being wrong\"",
  "mustache": "<div class=\"cardContainer\">\n  <div class=\"vignetteOverlay\"></div>\n  <div class=\"vignetteOverlay2\"></div>\n  <div class=\"cardContent\">\n    <div class=\"title\">\n      <svg viewBox=\"0 0 280 80\">\n          <text x=\"0%\" y=\"90%\" stroke=\"none\">ARGU</text>\n       </svg>\n      <svg viewBox=\"0 0 280 80\">\n          <text x=\"0%\" y=\"90%\" stroke=\"none\">MEN</text>\n       </svg>\n      <svg viewBox=\"0 0 280 80\">\n          <text x=\"0%\" y=\"90%\" stroke=\"none\">TUM</text>\n       </svg>\n    </div>\n    \n     <div class=\"pieces\">\n    \t<img src=\"../../Fallacies/Assets/Fallacy-back/birds.png\"/>\n    </div>\n    <div class=\"footer\">\n      <svg viewBox=\"0 0 280 80\">\n          <text x=\"50%\" y=\"90%\" stroke=\"none\" text-anchor=\"middle\">{{tagline_en}}</text>\n       </svg>\n    </div>\n\n  </div>\n \n</div>",
  "useMustache": false,
  "cardClass": "",
  "rscount": 1,
  "rsstyle": "bunch",
  "cindices": ""
}